LICENSE
MANIFEST.in
README.rst
helga_oneliner.py
setup.py
helga_oneliner.egg-info/PKG-INFO
helga_oneliner.egg-info/SOURCES.txt
helga_oneliner.egg-info/dependency_links.txt
helga_oneliner.egg-info/entry_points.txt
helga_oneliner.egg-info/top_level.txt
helga_oneliner.egg-info/zip-safe